mcp_server_flockx/__init__.py
mcp_server_flockx/main.py
mcp_server_flockx-0.2.0.dist-info/licenses/LICENSE
mcp_server_flockx-0.2.0.dist-info/METADATA
mcp_server_flockx-0.2.0.dist-info/WHEEL
mcp_server_flockx-0.2.0.dist-info/entry_points.txt
mcp_server_flockx-0.2.0.dist-info/top_level.txt
mcp_server_flockx-0.2.0.dist-info/RECORD
