Metadata-Version: 2.4
Name: mcp-server-flockx
Version: 0.2.0
Summary: MCP server for FlockX AI agent platform - enables AI assistants to interact with FlockX agents
Author-email: FlockX Team <support@flockx.io>, Mark Alosey <mark@flockx.io>
License: MIT
Project-URL: Homepage, https://flockx.io
Project-URL: Source, https://github.com/flockx-official/mcp-server-flockx
Project-URL: Bug Reports, https://github.com/flockx-official/mcp-server-flockx/issues
Project-URL: Documentation, https://docs.flockx.io
Keywords: mcp,flockx,ai,agents,cursor,claude
Classifier: Development Status :: 3 - Alpha
Classifier: Intended Audience :: Developers
Classifier: License :: OSI Approved :: MIT License
Classifier: Operating System :: OS Independent
Classifier: Programming Language :: Python :: 3
Classifier: Programming Language :: Python :: 3.8
Classifier: Programming Language :: Python :: 3.9
Classifier: Programming Language :: Python :: 3.10
Classifier: Programming Language :: Python :: 3.11
Classifier: Programming Language :: Python :: 3.12
Classifier: Topic :: Software Development :: Libraries :: Python Modules
Classifier: Topic :: Scientific/Engineering :: Artificial Intelligence
Requires-Python: >=3.8
License-File: LICENSE
Requires-Dist: requests<3,>=2.32
Requires-Dist: pydantic<3,>=2.8
Requires-Dist: pydantic-settings<3,>=2.3
Requires-Dist: fastmcp<3,>=2.7.1
Requires-Dist: fastapi<1.0,>=0.115
Requires-Dist: uvicorn<1.0,>=0.30
Requires-Dist: python-dotenv<2,>=1.0
Requires-Dist: httpx<0.29,>=0.28.1
Dynamic: license-file
